coverage_badge/__init__.py
coverage_badge/__main__.py
coverage_badge/templates/flat.svg
coverage_badge-1.1.1.dist-info/LICENSE.txt
coverage_badge-1.1.1.dist-info/METADATA
coverage_badge-1.1.1.dist-info/WHEEL
coverage_badge-1.1.1.dist-info/entry_points.txt
coverage_badge-1.1.1.dist-info/top_level.txt
coverage_badge-1.1.1.dist-info/zip-safe
coverage_badge-1.1.1.dist-info/RECORD
