Metadata-Version: 2.1
Name: coverage-badge
Version: 1.1.1
Summary: Generate coverage badges for Coverage.py.
Home-page: https://github.com/dbrgn/coverage-badge
Author: Danilo Bargen
Author-email: mail@dbrgn.ch
License: MIT
Keywords: coverage badge shield
Classifier: Development Status :: 5 - Production/Stable
Classifier: Environment :: Console
Classifier: License :: OSI Approved :: MIT License
Classifier: Operating System :: OS Independent
Classifier: Programming Language :: Python :: 3
Classifier: Topic :: Software Development :: Testing
License-File: LICENSE.txt
Requires-Dist: coverage
